<annotation>
	<folder>image2</folder>
	<filename>130.png</filename>
	<path>D:\project3\kitchen_data\image2\130.png</path>
	<source>
		<database>Unknown</database>
	</source>
	<size>
		<width>1016</width>
		<height>460</height>
		<depth>3</depth>
	</size>
	<segmented>0</segmented>
	<object>
		<name>head</name>
		<pose>Unspecified</pose>
		<truncated>0</truncated>
		<difficult>0</difficult>
		<bndbox>
			<xmin>262</xmin>
			<ymin>227</ymin>
			<xmax>350</xmax>
			<ymax>323</ymax>
		</bndbox>
	</object>
</annotation>
